valer.health-1.2.4rc20-nspkg.pth
bika/health/__init__.py
bika/health/config.py
bika/health/configure.zcml
bika/health/interfaces.py
bika/health/permissions.py
bika/health/permissions.zcml
bika/health/setuphandlers.py
bika/health/testing.py
bika/health/utils.py
bika/health/validators.py
bika/health/version.txt
bika/health/adapters/__init__.py
bika/health/adapters/addsample.py
bika/health/adapters/configure.zcml
bika/health/adapters/guards/__init__.py
bika/health/adapters/guards/configure.zcml
bika/health/adapters/listing/__init__.py
bika/health/adapters/listing/batches.py
bika/health/adapters/listing/clients.py
bika/health/adapters/listing/configure.zcml
bika/health/adapters/referencewidget/__init__.py
bika/health/adapters/referencewidget/configure.zcml
bika/health/adapters/widgetvisibility/__init__.py
bika/health/adapters/widgetvisibility/analysisrequest.py
bika/health/adapters/widgetvisibility/batch.py
bika/health/adapters/widgetvisibility/configure.zcml
bika/health/adapters/widgetvisibility/doctor.py
bika/health/adapters/widgetvisibility/patient.py
bika/health/ajax/__init__.py
bika/health/ajax/ajaxhandler.py
bika/health/ajax/bikasetup.py
bika/health/ajax/client.py
bika/health/ajax/configure.zcml
bika/health/browser/__init__.py
bika/health/browser/configure.zcml
bika/health/browser/referencewidget.py
bika/health/browser/aetiologicagent/__init__.py
bika/health/browser/aetiologicagent/configure.zcml
bika/health/browser/aetiologicagent/getaetiologicagents.py
bika/health/browser/aetiologicagent/getaetiologicagentsubtypes.py
bika/health/browser/analysisrequest/__init__.py
bika/health/browser/analysisrequest/configure.zcml
bika/health/browser/analysisrequest/invoice.py
bika/health/browser/analysisrequest/templates/analysisrequest_invoice_content.pt
bika/health/browser/analysisrequest/templates/reports/default.css
bika/health/browser/analysisrequest/templates/reports/default.pt
valer.health-1.2.4rc20.dist-info/DESCRIPTION.rst
valer.health-1.2.4rc20.dist-info/METADATA
valer.health-1.2.4rc20.dist-info/RECORD
valer.health-1.2.4rc20.dist-info/WHEEL
valer.health-1.2.4rc20.dist-info/entry_points.txt
valer.health-1.2.4rc20.dist-info/metadata.json
valer.health-1.2.4rc20.dist-info/namespace_packages.txt
valer.health-1.2.4rc20.dist-info/top_level.txt
