Metadata-Version: 2.0
Name: valer.health
Version: 1.2.4rc20
Summary: Valer Health
Home-page: https://github.com/valeriozhang/senaite.health
Author: Valer Group LLC
Author-email: valerio.zhang@valer.us
License: GPLv2
Keywords: lims,lis,senaite,opensource,health,Valer
Platform: UNKNOWN
Classifier: Development Status :: 5 - Production/Stable
Classifier: Environment :: Web Environment
Classifier: Framework :: Plone
Classifier: Framework :: Zope2
Classifier: Programming Language :: Python
Provides-Extra: test
Requires-Dist: archetypes.schemaextender
Requires-Dist: valer.lims (>=1.3.4rc11)
Requires-Dist: valer.panic (>=1.0.1rc11)
Provides-Extra: test
Requires-Dist: plone.app.testing; extra == 'test'
Requires-Dist: unittest2; extra == 'test'
